Chorus-0.9.0.dist-info/DESCRIPTION.rst
Chorus-0.9.0.dist-info/METADATA
Chorus-0.9.0.dist-info/RECORD
Chorus-0.9.0.dist-info/WHEEL
Chorus-0.9.0.dist-info/metadata.json
Chorus-0.9.0.dist-info/top_level.txt
chorus/__init__.py
chorus/demo.py
chorus/descriptor.py
chorus/indigo.py
chorus/mcsdr.py
chorus/molutil.py
chorus/patty.py
chorus/rdkit.py
chorus/remover.py
chorus/smilessupplier.py
chorus/substructure.py
chorus/topology.py
chorus/v2000reader.py
chorus/v2000writer.py
chorus/wclogp.py
chorus/wclogp.yaml
chorus/cython/__init__.py
chorus/cython/cython_setup.py
chorus/cython/mcsdr.cpython-36m-darwin.so
chorus/draw/__init__.py
chorus/draw/calc2dcoords.py
chorus/draw/drawable.py
chorus/draw/drawer2d.py
chorus/draw/helper.py
chorus/draw/matplotlib.py
chorus/draw/qt.py
chorus/draw/svg.py
chorus/model/__init__.py
chorus/model/aminoacid.py
chorus/model/atom.py
chorus/model/bond.py
chorus/model/graphmol.py
chorus/model/nucleicacid.py
chorus/model/periodictable.yaml
chorus/model/sugar.py
chorus/resources/DrugBank/AmphotericinB.mol
chorus/resources/DrugBank/Anidulafungin.mol
chorus/resources/DrugBank/Arg.mol
chorus/resources/DrugBank/CaAcO2.mol
chorus/resources/DrugBank/Carbidopa.mol
chorus/resources/DrugBank/Cefditoren.mol
chorus/resources/DrugBank/Ceftazidime.mol
chorus/resources/DrugBank/Colesevelam.mol
chorus/resources/DrugBank/Cyanocobalamin.mol
chorus/resources/DrugBank/CyclosporinA.mol
chorus/resources/DrugBank/Daunorubicin.mol
chorus/resources/DrugBank/Dipyridamole.mol
chorus/resources/DrugBank/Docetaxel.mol
chorus/resources/DrugBank/Fondaparinux.mol
chorus/resources/DrugBank/Formestane.mol
chorus/resources/DrugBank/Gadodiamide.mol
chorus/resources/DrugBank/Goserelin.mol
chorus/resources/DrugBank/Indinavir.mol
chorus/resources/DrugBank/Itraconazole.mol
chorus/resources/DrugBank/KCl.mol
chorus/resources/DrugBank/Lys.mol
chorus/resources/DrugBank/Nelfinavir.mol
chorus/resources/DrugBank/Nitroprusside.mol
chorus/resources/DrugBank/Paclitaxel.mol
chorus/resources/DrugBank/Phe.mol
chorus/resources/DrugBank/Phe_omit.mol
chorus/resources/DrugBank/Piperacillin.mol
chorus/resources/DrugBank/Plerixafor.mol
