Metadata-Version: 2.0
Name: Chorus
Version: 0.9.0
Summary: Simple chemical structure modeling toolkit
Home-page: https://github.com/mojaie/chorus
Author: Seiji Matsuoka
Author-email: mojaie@aol.com
License: MIT
Keywords: molecule-modeling cheminformatics
Platform: UNKNOWN
Classifier: Development Status :: 3 - Alpha
Classifier: Intended Audience :: Science/Research
Classifier: Topic :: Scientific/Engineering :: Chemistry
Classifier: Topic :: Scientific/Engineering :: Bio-Informatics
Classifier: License :: OSI Approved :: MIT License
Classifier: Programming Language :: Python
Classifier: Programming Language :: Python :: 3.5
Classifier: Programming Language :: Python :: 3.6
Requires-Python: >=3.5
Requires-Dist: matplotlib
Requires-Dist: networkx
Requires-Dist: numexpr
Requires-Dist: numpy
Requires-Dist: pyyaml
